{
  "lr": "2026-05-15",
  "rid": "25928512992",
  "m_issue": 249,
  "m_month": "2026-05",
  "comments": {
    "66": "2026-03-26",
    "47": "2026-05-03",
    "67": "2026-03-17",
    "103": "2026-03-15",
    "77": "2026-03-14",
    "54": "2026-04-03",
    "28": "2026-03-28",
    "65": "2026-03-29",
    "233": "2026-04-23",
    "255": "2026-05-05"
  },
  "cursor": "103",
  "prs": {
    "163": "RegisterCustomHandler (Closes #66)",
    "165": "ExcelAssembler (Closes #28)",
    "272": "FieldRetriever modernize (refactor) - merged",
    "273": "MetricsGetter modernize (refactor)"
  },
  "notes": "Run 25928512992 (2026-05-15): Task 10: PR #273 created modernizing MetricsGetter.cs (file-scoped ns, is null/is not null, pattern matching). Task 2: all issues have recent Clippy comments, no new human activity. Task 3: no fixable issues without existing PRs.",
  "checked_off": {
    "196": "source-gen-regex",
    "tunit132": "TUnit-1.32.0",
    "222": "TUnit-1.37.10",
    "235": "TUnit-1.37.36",
    "236": "SmlDataRetriever-tests",
    "237": "UriFixer-refactor",
    "242": "TUnit-1.39.0",
    "243": "TUnit-1.40.5",
    "244": "guid-random-refactor",
    "245": "TUnit-1.40.10",
    "246": "TryGetValue-refactor",
    "247": "SpreadsheetDocMgr-cleanup-WorksheetAccessorTests",
    "234": "corrupt-zip-fix",
    "248": "TUnit-1.41.0",
    "250": "perf-flatopc-base64",
    "251": "test-content-data-key",
    "252": "urifixer-open-helpers-closed",
    "253": "sdk-hyperlink-uri-fix-merged",
    "254": "TUnit-1.43.11-merged",
    "256": "fix-issue-255-merged",
    "258": "ptextensions-tests-merged",
    "259": "ptextensions-additional-tests-merged",
    "262": "release-v3.4.3-merged",
    "263": "reference-adder-tests-and-dirty-fix-merged",
    "264": "tunit-1.43.41-merged",
    "265": "throwifnull-refactor-merged",
    "267": "tunit-1.44.0-merged",
    "268": "fileutils-simplify-merged",
    "270": "perf-linq-count-merged",
    "271": "wmlcomparer-selectmany-merged",
    "272": "fieldretriever-modernize-merged"
  }
}
